[
  {
    "user_name": "Мистер Исключительный",
    "user_role": "teacher",
    "booking_type": "Тип1",
    "date": "2025-08-15",
    "start_time": "13:00",
    "end_time": "14:30",
    "user_id": 1180878673,
    "created_at": "2025-08-12 14:28:17",
    "subjects": [
      "phys",
      "inf"
    ],
    "id": 7
  },
  {
    "user_name": "Пабло Пикассо",
    "user_role": "teacher",
    "booking_type": "Тип2",
    "date": "2025-08-14",
    "start_time": "09:00",
    "end_time": "16:30",
    "user_id": 1180878673,
    "created_at": "2025-08-12 14:07:26",
    "subjects": [
      "phys",
      "inf"
    ],
    "id": 3
  },
  {
    "user_name": "Молния Маккуин",
    "user_role": "student",
    "booking_type": "Тип2",
    "date": "2025-08-17",
    "start_time": "13:00",
    "end_time": "16:30",
    "user_id": 1180878673,
    "created_at": "2025-08-12 14:30:30",
    "subject": "math",
    "id": 8
  },
  {
    "user_name": "Барри Аллен",
    "user_role": "student",
    "booking_type": "Тип2",
    "date": "2025-08-22",
    "start_time": "13:00",
    "end_time": "16:30",
    "user_id": 1180878673,
    "created_at": "2025-08-12 14:55:41",
    "subject": "phys",
    "id": 8
  },
  {
    "user_name": "Брюс Уэйн",
    "user_role": "student",
    "booking_type": "Тип2",
    "date": "2025-08-25",
    "start_time": "13:00",
    "end_time": "16:00",
    "user_id": 1180878673,
    "created_at": "2025-08-12 14:57:04",
    "subject": "math",
    "id": 9
  },
  {
    "user_name": "Рони Колеман",
    "user_role": "student",
    "booking_type": "Тип2",
    "date": "2025-08-29",
    "start_time": "13:00",
    "end_time": "16:30",
    "user_id": 1180878673,
    "created_at": "2025-08-12 14:57:57",
    "subject": "phys",
    "id": 10
  },
  {
    "user_name": "Андрюха Смаев",
    "user_role": "teacher",
    "booking_type": "Тип3",
    "date": "2025-08-28",
    "start_time": "11:00",
    "end_time": "12:30",
    "user_id": 1180878673,
    "created_at": "2025-08-12 15:13:03",
    "subjects": [
      "phys",
      "inf"
    ],
    "id": 11
  },
  {
    "user_name": "Питер Паркер",
    "user_role": "student",
    "booking_type": "Тип4",
    "date": "2025-08-13",
    "start_time": "15:30",
    "end_time": "18:30",
    "user_id": 1180878673,
    "created_at": "2025-08-12 14:08:44",
    "subject": "inf",
    "id": 6
  },
  {
    "user_name": "Майлз Моралес",
    "user_role": "teacher",
    "booking_type": "Тип4",
    "date": "2025-08-21",
    "start_time": "15:00",
    "end_time": "18:30",
    "user_id": 1180878673,
    "created_at": "2025-08-12 14:07:57",
    "subjects": [
      "phys",
      "inf"
    ],
    "id": 4
  },
  {
    "user_name": "Иван золо",
    "user_role": "teacher",
    "booking_type": "Тип4",
    "date": "2025-08-27",
    "start_time": "10:00",
    "end_time": "12:30",
    "user_id": 1180878673,
    "created_at": "2025-08-12 15:13:45",
    "subjects": [
      "phys",
      "inf"
    ],
    "id": 12
  }
]